pyprojecttemplate/__init__.py
pyprojecttemplate/basicmath.py
pyprojecttemplate/demo.py
pyprojecttemplate-0.2.0.dist-info/LICENSE
pyprojecttemplate-0.2.0.dist-info/METADATA
pyprojecttemplate-0.2.0.dist-info/WHEEL
pyprojecttemplate-0.2.0.dist-info/top_level.txt
pyprojecttemplate-0.2.0.dist-info/RECORD
