Metadata-Version: 2.1
Name: pyprojecttemplate
Version: 0.2.0
Summary: Example Project Structure for a Python / PyPI Project
Home-page: https://github.com/patrickshiel/python-package-template
Author: Patrick Shiel
Author-email: patrick.shiel.io@gmail.com
License: MIT
Keywords: project template python
Platform: UNKNOWN
Classifier: Programming Language :: Python :: 3
Classifier: License :: OSI Approved :: MIT License
Classifier: Operating System :: OS Independent
Requires-Python: >=2.7, !=3.0.*, !=3.1.*, !=3.2.*, !=3.3.*, !=3.4.*, <4
Requires-Dist: requests
